django_gist_embed-0.1.dist-info/RECORD
django_gist_embed-0.1.dist-info/top_level.txt
django_gist_embed-0.1.dist-info/DESCRIPTION.rst
django_gist_embed-0.1.dist-info/metadata.json
django_gist_embed-0.1.dist-info/WHEEL
django_gist_embed-0.1.dist-info/METADATA
gist_embed/apps.py
gist_embed/__init__.py
gist_embed/views.py
gist_embed/templatetags/__init__.py
gist_embed/templatetags/gist_embed.py
gist_embed/migrations/__init__.py
